vic_au_important_dates_mcp/__init__.py
vic_au_important_dates_mcp/client.py
vic_au_important_dates_mcp/config.yaml
vic_au_important_dates_mcp/models.py
vic_au_important_dates_mcp/server.py
vic_au_important_dates_mcp-0.1.3.dist-info/METADATA
vic_au_important_dates_mcp-0.1.3.dist-info/WHEEL
vic_au_important_dates_mcp-0.1.3.dist-info/entry_points.txt
vic_au_important_dates_mcp-0.1.3.dist-info/RECORD
