Metadata-Version: 2.4
Name: vic-au-important-dates-mcp
Version: 0.1.3
Summary: MCP Server for Victoria,Australia important dates API
Project-URL: Homepage, https://github.com/ivarrian/vic-au-important-dates-mcp
Project-URL: Repository, https://github.com/ivarrian/vic-au-important-dates-mcp
Project-URL: Issues, https://github.com/ivarrian/vic-au-important-dates-mcp/issues
Author-email: Ravi Nair <ivarrian@gmail.com>
License: MIT
Keywords: api,australia,dates,holidays,victoria
Classifier: Development Status :: 3 - Alpha
Classifier: Intended Audience :: Developers
Classifier: Programming Language :: Python :: 3
Classifier: Programming Language :: Python :: 3.12
Classifier: Topic :: Software Development :: Libraries :: Python Modules
Requires-Python: >=3.12
Requires-Dist: fastmcp>=2.9.2
Requires-Dist: ipython>=9.3.0
Requires-Dist: openai-agents>=0.0.19
Requires-Dist: pydantic>=2.11.7
Requires-Dist: python-dotenv>=1.0.0
Requires-Dist: pyyaml>=6.0.2
Requires-Dist: requests>=2.32.4
